orangecontrib/__init__.py
orangecontrib/blue_whale/__init__.py
orangecontrib/blue_whale/canvasmain.py
orangecontrib/blue_whale/i18n_config.py
orangecontrib/blue_whale/locale/bluewhale.en.yml
orangecontrib/blue_whale/locale/bluewhale.zh.yml
orangecontrib/blue_whale/widgets/__init__.py
orangecontrib/blue_whale/widgets/owcase.py
orangecontrib/blue_whale/widgets/owcasedata.py
orangecontrib/blue_whale/widgets/user
orangecontrib/blue_whale/widgets/icons/bw.svg
orangecontrib/blue_whale/widgets/icons/case.svg
orangecontrib/blue_whale/widgets/icons/data.svg
orangecontrib/blue_whale/widgets/icons/login-bg.jpg
orangecontrib/blue_whale/widgets/utils/__init__.py
orangecontrib/blue_whale/widgets/utils/config.py
orangecontrib/blue_whale/widgets/utils/local_file.py
orangecontrib/blue_whale/widgets/utils/login.py
orangecontrib/blue_whale/widgets/utils/remote.py
orangecontrib/blue_whale/widgets/utils/service_window.py
BlueWhale3_BlueWhale-0.0.54.dist-info/METADATA
BlueWhale3_BlueWhale-0.0.54.dist-info/WHEEL
BlueWhale3_BlueWhale-0.0.54.dist-info/entry_points.txt
BlueWhale3_BlueWhale-0.0.54.dist-info/top_level.txt
BlueWhale3_BlueWhale-0.0.54.dist-info/RECORD
